bienvenue/__init__.py
bienvenue/decoders.py
bienvenue/env.py
bienvenue/old.py
bienvenue/unprefix.py
bienvenue-3.0.1.dist-info/DESCRIPTION.rst
bienvenue-3.0.1.dist-info/METADATA
bienvenue-3.0.1.dist-info/RECORD
bienvenue-3.0.1.dist-info/WHEEL
bienvenue-3.0.1.dist-info/metadata.json
bienvenue-3.0.1.dist-info/top_level.txt
