Metadata-Version: 2.0
Name: bienvenue
Version: 3.0.1
Summary: Read config from environment for 12 factor apps
Home-page: https://github.com/scampersand/bienvenue
Author: Aron Griffis
Author-email: aron@scampersand.com
License: MIT
Keywords: django,environment,environ,env
Platform: UNKNOWN
Classifier: Development Status :: 5 - Production/Stable
Classifier: Intended Audience :: Developers
Classifier: License :: OSI Approved :: MIT License
Classifier: Programming Language :: Python
Classifier: Programming Language :: Python :: 3
Classifier: Programming Language :: Python :: 3.4
Classifier: Programming Language :: Python :: 3.5
Classifier: Programming Language :: Python :: 3.6
Classifier: Programming Language :: Python :: 3.7
